resultful/__init__.py
resultful/__version__.py
resultful/py.typed
resultful/result.py
resultful/impl/__init__.py
resultful/impl/no_result.py
resultful/impl/result.py
resultful-1.0.0a2.dist-info/LICENSE
resultful-1.0.0a2.dist-info/METADATA
resultful-1.0.0a2.dist-info/WHEEL
resultful-1.0.0a2.dist-info/top_level.txt
resultful-1.0.0a2.dist-info/RECORD
